europarse/__init__.py
europarse/parser.py
europarse/relativedelta.py
europarse/tz/__init__.py
europarse/tz/tz.py
europarse/tz/win.py
europarse/zoneinfo/__init__.py
europarse/zoneinfo/europarse-zoneinfo.tar.gz
europarse/zoneinfo/rebuild.py
europarse-1.0.0.dist-info/LICENSE
europarse-1.0.0.dist-info/METADATA
europarse-1.0.0.dist-info/WHEEL
europarse-1.0.0.dist-info/top_level.txt
europarse-1.0.0.dist-info/zip-safe
europarse-1.0.0.dist-info/RECORD
